json_rpc_service-0.2.3.dist-info/METADATA
json_rpc_service-0.2.3.dist-info/RECORD
json_rpc_service-0.2.3.dist-info/WHEEL
json_rpc_service-0.2.3.dist-info/top_level.txt
jsonrpcservice/__init__.py
