Metadata-Version: 2.1
Name: json-rpc-service
Version: 0.2.3
Summary: Simple extendable JSON-RPC Service builder and handler.
Home-page: UNKNOWN
Author: Heureka.cz
Author-email: fialovi@heureka.cz
License: MIT
Platform: UNKNOWN
